speedtest_ssh/__init__.py
speedtest_ssh/_version.py
speedtest_ssh/config.py
speedtest_ssh/data_transfer.py
speedtest_ssh/ping.py
speedtest_ssh/py.typed
speedtest_ssh/sftp_wrapper.py
speedtest_ssh/speedtest_ssh.py
speedtest_ssh/util.py
speedtest_ssh-2.10.1.dist-info/licenses/LICENSE
speedtest_ssh-2.10.1.dist-info/METADATA
speedtest_ssh-2.10.1.dist-info/WHEEL
speedtest_ssh-2.10.1.dist-info/entry_points.txt
speedtest_ssh-2.10.1.dist-info/top_level.txt
speedtest_ssh-2.10.1.dist-info/RECORD
