Metadata-Version: 2.4
Name: speedtest_ssh
Version: 2.10.1
Summary: A tool meant to check inter-device speeds via ssh
License: GPL
Project-URL: Homepage, https://github.com/zwimer/speedtest_ssh
Classifier: Programming Language :: Python :: 3
Classifier: Programming Language :: Python :: 3.12
Requires-Python: >=3.12
License-File: LICENSE
Requires-Dist: argcomplete
Requires-Dist: paramiko
Requires-Dist: tqdm
Dynamic: license-file
